asendia_us_lib/__init__.py
asendia_us_lib/shipping_close_dispatch_request.py
asendia_us_lib/shipping_close_dispatch_response.py
asendia_us_lib/shipping_rate_request.py
asendia_us_lib/shipping_rate_response.py
asendia_us_lib/shipping_request.py
asendia_us_lib/shipping_response.py
asendia_us_lib/tracking_details_response.py
asendia_us_lib/tracking_milestone_response.py
carrier.asendia_us-2021.2.2.dist-info/WHEEL
carrier.asendia_us-2021.2.2.dist-info/METADATA
carrier.asendia_us-2021.2.2.dist-info/RECORD
