Metadata-Version: 2.1
Name: carrier.asendia-us
Version: 2021.2.2
Summary: Asendia US API Schemas Python Data Types library
Home-page: https://github.com/PurplShip/purplship-carriers/tree/master/carrier.asendia_us
License: MIT
Author: Dan Kobina
Author-email: danielkobina@gmail.com
Requires-Python: >=3.6,<4.0
Classifier: Intended Audience :: Developers
Classifier: License :: OSI Approved :: MIT License
Classifier: Operating System :: OS Independent
Classifier: Programming Language :: Python :: 3
Classifier: Programming Language :: Python :: 3.6
Classifier: Programming Language :: Python :: 3.7
Classifier: Programming Language :: Python :: 3.8
Classifier: Programming Language :: Python :: 3.9
Requires-Dist: jstruct
Project-URL: Repository, https://github.com/PurplShip/purplship-carriers
